<service>
	<servicekey>5137784B-C09F-24D5-396734F6193D879D</servicekey>
	<basedirectory>/project/</basedirectory>
	<defaultaction>showwelcome</defaultaction>
	<frontend>www</frontend>
	<headerinclude>dsp_inc_top.cfm</headerinclude>
	<leftinclude>dsp_inc_left.cfm</leftinclude>
<actions>	
	<item>
		<name>ShowWelcome</name>
		<description></description>
		<template>dsp_welcome.cfm</template>
		<checkframeset>1</checkframeset>
		<setservice>0</setservice>
		<directory></directory>
		<productkeysincluded></productkeysincluded>
		<attributes></attributes>
	</item>
	<item>
		<name>newproject</name>
		<description></description>
		<template>dsp_new_project.cfm</template>
		<checkframeset>1</checkframeset>
		<setservice>0</setservice>
		<directory></directory>
		<productkeysincluded></productkeysincluded>
		<attributes></attributes>
	</item>	
	<item>
		<name>timeline</name>
		<description></description>
		<template>dsp_timeline.cfm</template>
		<checkframeset>1</checkframeset>
		<setservice>0</setservice>
		<directory></directory>
		<productkeysincluded></productkeysincluded>
		<attributes></attributes>
	</item>
	<item>
		<name>ShowProject</name>
		<description></description>
		<template>dsp_show_project.cfm</template>
		<checkframeset>1</checkframeset>
		<setservice>0</setservice>
		<directory></directory>
		<productkeysincluded></productkeysincluded>
		<attributes></attributes>
	</item>
	<item>
		<name>editproject</name>
		<description></description>
		<template>dsp_edit_project.cfm</template>
		<checkframeset>1</checkframeset>
		<setservice>0</setservice>
		<directory></directory>
		<productkeysincluded></productkeysincluded>
		<attributes></attributes>
	</item>
	<item>
		<name>CloseProject</name>
		<type>inpage</type>
		<description></description>
		<template>dsp_close_project.cfm</template>
		<checkframeset>1</checkframeset>
		<setservice>0</setservice>
		<directory>dialogs</directory>
		<productkeysincluded></productkeysincluded>
		<attributes></attributes>
	</item>
	<item>
		<name>DoDeleteProject</name>
		<type>action</type>
		<description></description>
		<template>act_delete_project.cfm</template>
		<checkframeset>1</checkframeset>
		<setservice>0</setservice>
		<directory>actions</directory>
		<productkeysincluded></productkeysincluded>
		<attributes></attributes>
	</item>
</actions>
</service>